{"cameraMode":{"drawMode":0,"name":"Shaded","section":"Shading Mode"},"sceneLighting":true,"audioPlay":false,"sceneViewState":{"m_AlwaysRefresh":false,"showFog":true,"showSkybox":true,"showFlares":true,"showImageEffects":true,"showParticleSystems":true,"showVisualEffectGraphs":true,"m_FxEnabled":true},"in2DMode":false,"pivot":{"x":705.6450805664063,"y":1920.0379638671875,"z":-500.0848083496094},"rotation":{"x":0.12232454866170883,"y":0.0451958142220974,"z":-0.005976832006126642,"w":0.9915488362312317},"size":113.02229309082031,"orthographic":false}